earth_wallpaper/__init__.py
earth_wallpaper/about.py
earth_wallpaper/config.py
earth_wallpaper/main.py
earth_wallpaper/systemtray.py
earth_wallpaper/thread.py
earth_wallpaper/interfaces/__init__.py
earth_wallpaper/interfaces/anime.py
earth_wallpaper/interfaces/bingRand.py
earth_wallpaper/interfaces/bingToday.py
earth_wallpaper/interfaces/fengYun4.py
earth_wallpaper/interfaces/himawari8.py
earth_wallpaper/interfaces/localWallpaper.py
earth_wallpaper/interfaces/wallhaven.py
earth_wallpaper/interfaces/wallpaper24.py
earth_wallpaper/interfaces/utils/__init__.py
earth_wallpaper/interfaces/utils/platformInfo.py
earth_wallpaper/interfaces/utils/settings.py
earth_wallpaper/interfaces/utils/sunCalculator.py
earth_wallpaper/resource/earth-wallpaper.png
earth_wallpaper/ui/UI_about.py
earth_wallpaper/ui/UI_config.py
earth_wallpaper/ui/__init__.py
earth_wallpaper/utils/__init__.py
earth_wallpaper/utils/platformInfo.py
earth_wallpaper/utils/setWallpaper.py
earth_wallpaper/utils/systems/__init__.py
earth_wallpaper/utils/systems/linux/__init__.py
earth_wallpaper/utils/systems/linux/cinnamon.py
earth_wallpaper/utils/systems/linux/cutefish.py
earth_wallpaper/utils/systems/linux/deepin.py
earth_wallpaper/utils/systems/linux/gnome.py
earth_wallpaper/utils/systems/linux/kde.py
earth_wallpaper/utils/systems/linux/lxde.py
earth_wallpaper/utils/systems/linux/lxqt.py
earth_wallpaper/utils/systems/linux/mate.py
earth_wallpaper/utils/systems/linux/xfce.py
earth_wallpaper/utils/systems/windows/__init__.py
earth_wallpaper/utils/systems/windows/windows.py
earth_wallpaper-2.2.2.dist-info/LICENSE
earth_wallpaper-2.2.2.dist-info/METADATA
earth_wallpaper-2.2.2.dist-info/WHEEL
earth_wallpaper-2.2.2.dist-info/entry_points.txt
earth_wallpaper-2.2.2.dist-info/top_level.txt
earth_wallpaper-2.2.2.dist-info/RECORD
