Metadata-Version: 2.1
Name: earth-wallpaper
Version: 2.2.2
Summary: Simple and easy to use multifunctional wallpaper software 简单好用的多功能壁纸软件
Home-page: https://github.com/Pylogmon/earth_wallpaper
Author: Pylogmon
Author-email: pylogmon@outlook.com
License: GPLv3
License-File: LICENSE
Requires-Dist: Pillow
Requires-Dist: PySide6
Requires-Dist: requests
Requires-Dist: pysocks
Requires-Dist: dbus-python ; platform_system == "Linux"
Requires-Dist: pywin32 ; platform_system == "Windows"
